nmem_cli/__init__.py
nmem_cli/cli.py
nmem_cli/py.typed
nmem_cli/tui/__init__.py
nmem_cli/tui/__main__.py
nmem_cli/tui/api_client.py
nmem_cli/tui/app.py
nmem_cli/tui/screens/__init__.py
nmem_cli/tui/screens/dashboard.py
nmem_cli/tui/screens/graph.py
nmem_cli/tui/screens/help.py
nmem_cli/tui/screens/memories.py
nmem_cli/tui/screens/memory_detail.py
nmem_cli/tui/screens/settings.py
nmem_cli/tui/screens/thread_detail.py
nmem_cli/tui/screens/threads.py
nmem_cli/tui/widgets/__init__.py
nmem_cli-0.5.11.dist-info/METADATA
nmem_cli-0.5.11.dist-info/WHEEL
nmem_cli-0.5.11.dist-info/entry_points.txt
nmem_cli-0.5.11.dist-info/RECORD
