Metadata-Version: 2.4
Name: nmem-cli
Version: 0.5.11
Summary: CLI and TUI for Nowledge Mem - AI memory management
Project-URL: Homepage, https://mem.nowledge.co/
Project-URL: Repository, https://github.com/nowledge-co/
Project-URL: Documentation, https://mem.nowledge.co/docs
Author: Nowledge Labs
License-Expression: MIT
Keywords: ai,cli,knowledge-graph,mcp,memory,tui
Classifier: Development Status :: 4 - Beta
Classifier: Environment :: Console
Classifier: Intended Audience :: Developers
Classifier: License :: OSI Approved :: MIT License
Classifier: Operating System :: OS Independent
Classifier: Programming Language :: Python :: 3
Classifier: Programming Language :: Python :: 3.11
Classifier: Programming Language :: Python :: 3.12
Classifier: Programming Language :: Python :: 3.13
Classifier: Topic :: Utilities
Requires-Python: >=3.11
Requires-Dist: httpx>=0.25.0
Requires-Dist: pyperclip>=1.9.0
Requires-Dist: rich>=13.0.0
Requires-Dist: textual>=0.50.0
Provides-Extra: dev
Requires-Dist: black>=23.0.0; extra == 'dev'
Requires-Dist: pytest-asyncio>=0.21.0; extra == 'dev'
Requires-Dist: pytest>=7.4.0; extra == 'dev'
Requires-Dist: ruff>=0.1.0; extra == 'dev'
